zodiaq/__init__.py
zodiaq/zodiaq.py
zodiaq/zodiaqParser.py
zodiaq/gui/__init__.py
zodiaq/gui/gui.py
zodiaq/gui/windows/MainWindow.py
zodiaq/gui/windows/TableWindow.py
zodiaq/gui/windows/__init__.py
zodiaq/gui/windows/tabs/IdentificationTabWindow.py
zodiaq/gui/windows/tabs/ScoringTabWindow.py
zodiaq/gui/windows/tabs/TabWindow.py
zodiaq/gui/windows/tabs/TargetedReanalysisTabWindow.py
zodiaq/gui/windows/tabs/__init__.py
zodiaq/identification/__init__.py
zodiaq/identification/identifier.py
zodiaq/identification/matchingFunctions.py
zodiaq/identification/outputFormattingFunctions.py
zodiaq/identification/poolingFunctions.py
zodiaq/loaders/__init__.py
zodiaq/loaders/library/__init__.py
zodiaq/loaders/library/decoyGenerationFunctions.py
zodiaq/loaders/library/libraryLoaderContext.py
zodiaq/loaders/library/libraryLoaderStrategy.py
zodiaq/loaders/library/libraryLoaderStrategyMgf.py
zodiaq/loaders/library/libraryLoaderStrategyTable.py
zodiaq/loaders/library/mappings.py
zodiaq/loaders/library/modificationMassDict.py
zodiaq/loaders/query/__init__.py
zodiaq/loaders/query/queryLoaderContext.py
zodiaq/loaders/query/queryLoaderStrategy.py
zodiaq/loaders/query/queryLoaderStrategyMzxml.py
zodiaq/plotting/__init__.py
zodiaq/plotting/spectra.py
zodiaq/plotting/spectrum.py
zodiaq/scoring/__init__.py
zodiaq/scoring/fdrCalculationFunctions.py
zodiaq/scoring/idpickerFunctions.py
zodiaq/scoring/quantificationFunctions.py
zodiaq/scoring/scoringFunctions.py
zodiaq/targetedReanalysis/__init__.py
zodiaq/targetedReanalysis/targetedReanalysisFunctions.py
zodiaq/utils/Printer.py
zodiaq/utils/__init__.py
zodiaq/utils/utils.py
zoDIAq-2.1.2.dist-info/LICENSE
zoDIAq-2.1.2.dist-info/METADATA
zoDIAq-2.1.2.dist-info/WHEEL
zoDIAq-2.1.2.dist-info/entry_points.txt
zoDIAq-2.1.2.dist-info/top_level.txt
zoDIAq-2.1.2.dist-info/RECORD
