Metadata-Version: 2.1
Name: zoDIAq
Version: 2.1.2
Summary: Bioinformatics software package for identifying peptides and proteins in DIA and DISPA mass spectrometry data files.
Author-email: Caleb Cranney <caleb.cranney.github@proton.me>
Project-URL: Homepage, https://github.com/xomicsdatascience/zoDIAq
Project-URL: Bug Tracker, https://github.com/xomicsdatascience/zoDIAq/issues
Classifier: Programming Language :: Python :: 3
Classifier: License :: OSI Approved :: MIT License
Classifier: Intended Audience :: Science/Research
Classifier: Topic :: Scientific/Engineering :: Bio-Informatics
Requires-Python: >=3.8
License-File: LICENSE
Requires-Dist: pyteomics >=4.4.1
Requires-Dist: matplotlib >=3.3.4
Requires-Dist: numba >=0.53.1
Requires-Dist: numpy <2.0
Requires-Dist: pandas >=1.2.2
Requires-Dist: Bio >=0.4.1
Requires-Dist: PyQt5 >=5.15.4
Requires-Dist: lxml >=4.6.2
Requires-Dist: scikit-learn >=1.1.2
